python_metrc/__init__.py
python_metrc/metrc.py
python_metrc-0.1.4.dist-info/AUTHORS.rst
python_metrc-0.1.4.dist-info/LICENSE
python_metrc-0.1.4.dist-info/METADATA
python_metrc-0.1.4.dist-info/WHEEL
python_metrc-0.1.4.dist-info/top_level.txt
python_metrc-0.1.4.dist-info/RECORD
