Metadata-Version: 2.1
Name: python-metrc
Version: 0.1.4
Summary: A light Python wrapper around the METRC Web API
Home-page: https://github.com/DigiThinkIT/python-metrc
Author: DigiThinkIT, Inc.
Author-email: hello@digithinkit.com
License: MIT license
Keywords: python_metrc
Platform: UNKNOWN
Classifier: Development Status :: 2 - Pre-Alpha
Classifier: Intended Audience :: Developers
Classifier: License :: OSI Approved :: MIT License
Classifier: Natural Language :: English
Classifier: Programming Language :: Python :: 2
Classifier: Programming Language :: Python :: 2.7
Classifier: Programming Language :: Python :: 3
Classifier: Programming Language :: Python :: 3.4
Classifier: Programming Language :: Python :: 3.5
Classifier: Programming Language :: Python :: 3.6
Classifier: Programming Language :: Python :: 3.7
Requires-Dist: hammock (>=0.2.4)
